kchopy/__init__.py
kchopy-0.1.dist-info/METADATA
kchopy-0.1.dist-info/WHEEL
kchopy-0.1.dist-info/top_level.txt
kchopy-0.1.dist-info/RECORD
