Metadata-Version: 2.1
Name: kchopy
Version: 0.1
Summary: Tools for neuroimaging pipelines by kcho
Home-page: http://github.com/kcho/kchopy
Author: Kevin Kang Ik Cho
Author-email: kevincho@bwh.harvard.edu
License: MIT
Platform: UNKNOWN
